{
  "required": true,
  "minVersion": "0.8",
  "package": "io.github.feltmc.feltapi.mixin.item",
  "compatibilityLevel": "JAVA_17",
  "mixins": [
    "EnchantmentHelperMixin",
    "EnchantmentMixin",
    "ExperienceOrbMixin",
    "ItemStackMixin",
    "LivingEntityMixin",
    "PacketByteBufMixin",
    "PlayerEntityMixin",
    "PlayerInventoryMixin",
    "PlayerScreenHandlerAccessor",
    "PlayerScreenHandlerMixin",
    "ServerPlayerInteractionManagerMixin"
  ],
  "client": [
    "client.ArmorFeatureRendererMixin",
    "client.ClientPlayerInteractionManagerMixin"
  ],
  "injectors": {
    "defaultRequire": 1
  }
}
